setup.py
biovida/__init__.py
biovida.egg-info/PKG-INFO
biovida.egg-info/SOURCES.txt
biovida.egg-info/dependency_links.txt
biovida.egg-info/requires.txt
biovida.egg-info/top_level.txt
biovida/diagnostics/__init__.py
biovida/diagnostics/disease_ont_interface.py
biovida/diagnostics/disease_symptoms_interface.py
biovida/genomics/__init__.py
biovida/genomics/disgenet_interface.py
biovida/images/__init__.py
biovida/images/_image_tools.py
biovida/images/_unify_images_against_other_biovida_apis.py
biovida/images/cancer_image_interface.py
biovida/images/image_cache_mgmt.py
biovida/images/image_processing.py
biovida/images/openi_interface.py
biovida/images/_interface_support/__init__.py
biovida/images/_interface_support/dicom_data_to_dict.py
biovida/images/_interface_support/shared.py
biovida/images/_interface_support/cancer_image/__init__.py
biovida/images/_interface_support/cancer_image/cancer_image_parameters.py
biovida/images/_interface_support/cancer_image/cancer_image_support_tools.py
biovida/images/_interface_support/openi/__init__.py
biovida/images/_interface_support/openi/_openi_image_id_processing.py
biovida/images/_interface_support/openi/_openi_imaging_modality_information.py
biovida/images/_interface_support/openi/_openi_text_feature_extraction.py
biovida/images/_interface_support/openi/openi_parameters.py
biovida/images/_interface_support/openi/openi_support_tools.py
biovida/images/_interface_support/openi/openi_text_processing.py
biovida/images/models/__init__.py
biovida/images/models/_image_classification_training.py
biovida/images/models/_mult_label_image_classification.py
biovida/images/models/_training_data_path.py
biovida/images/models/_training_private.py
biovida/images/models/border_detection.py
biovida/images/models/image_classification.py
biovida/images/models/template_matching.py
biovida/support_tools/__init__.py
biovida/support_tools/_cache_management.py
biovida/support_tools/_support_data.py
biovida/support_tools/printing.py
biovida/support_tools/support_tools.py
biovida/support_tools/utilities.py
biovida/unification/__init__.py
biovida/unification/unify_domains.py