Metadata-Version: 1.1
Name: biovida
Version: 0.1.1
Summary: Automated BioMedical Information Curation for Machine Learning Applications.
Home-page: https://github.com/TariqAHassan/BioVida.git
Author: Tariq A. Hassan
Author-email: laterallattice@gmail.com
License: BSD
Download-URL: https://github.com/TariqAHassan/BioVida/archive/v0.1.1.tar.gz
Keywords: machine-learning,biomedical-informatics,data-science,bioinformatics,imaging-informatics
Platform: UNKNOWN
Classifier: Development Status :: 3 - Alpha
Classifier: Natural Language :: English
Classifier: Intended Audience :: Science/Research
Classifier: Programming Language :: Python :: 3.4
Classifier: Programming Language :: Python :: 3.5
Classifier: Programming Language :: Python :: 3.6
Classifier: License :: OSI Approved :: BSD License
